musk/__init__.py
musk-0.0.1.dist-info/LICENSE.md
musk-0.0.1.dist-info/METADATA
musk-0.0.1.dist-info/WHEEL
musk-0.0.1.dist-info/top_level.txt
musk-0.0.1.dist-info/RECORD
