Metadata-Version: 2.1
Name: musk
Version: 0.0.1
Summary: A simulations package
Home-page: https://github.com/pypa/sampleproject
Author: Alan Sammarone
Author-email: alansammarone@gmail.com
License: UNKNOWN
Platform: UNKNOWN
Classifier: Programming Language :: Python :: 3
Requires-Python: >=3.7
